src/jihen_0/DoYouWant.py
src/jihen_0/__init__.py
jihen-1.0.0.dist-info/METADATA
jihen-1.0.0.dist-info/WHEEL
jihen-1.0.0.dist-info/licenses/LICENSE
jihen-1.0.0.dist-info/RECORD
