Metadata-Version: 2.1
Name: Jihen
Version: 1.0.0
Summary: Do you want?
Project-URL: Homepage, https://www.facebook.com/jihen.stambouli.3/
Author-email: Jihen <jihene.stambouli@gmail.com>
License-File: LICENSE
Classifier: License :: OSI Approved :: MIT License
Classifier: Operating System :: OS Independent
Classifier: Programming Language :: Python :: 3
Requires-Python: >=3.7
